MANIFEST.in
README.md
setup.py
SuperMarkdown/SuperMarkdown.py
SuperMarkdown/__init__.py
SuperMarkdown.egg-info/PKG-INFO
SuperMarkdown.egg-info/SOURCES.txt
SuperMarkdown.egg-info/dependency_links.txt
SuperMarkdown.egg-info/eager_resources.txt
SuperMarkdown.egg-info/entry_points.txt
SuperMarkdown.egg-info/requires.txt
SuperMarkdown.egg-info/top_level.txt
SuperMarkdown/ressources/snippet.html
SuperMarkdown/ressources/test.md
SuperMarkdown/ressources/css/github_flavoured_markdown.css
SuperMarkdown/ressources/css/mermaid.css
SuperMarkdown/ressources/css/toc.css
SuperMarkdown/ressources/js/jquery-1.11.3.min.js
SuperMarkdown/ressources/js/mermaid.min.js